Workbook

Sheet 投标决策评审-信息收集与前置评审
A1: 投标决策评审 — 信息收集与前置评审表
A3: Part A：项目基础信息（由申请人填写）
A4: 商机名称 | D4: 坪山区三维数据更新2026 | G4: 商机代码 | I4: PL00008111
A5: 商机阶段 | D5: 投标决策 | G5: 营销区域 | I5: 华南营销处
A6: 业务线 | D6: G1 | G6: 最终客户名称 | I6: 深圳市坪山区政务服务和数据管理局
A7: 销售经理 | D7: ='附1-预算表'!F2 -> 熊惠 | G7: 项目经理 | I7: ='附1-预算表'!H2 -> 邓先明
A8: 预计合同金额（万元） | D8: ='附1-预算表'!B6/10000 -> 205.852 | G8: 预计签单时间 | I8: 46266
A9: 预计贡献毛利率（%） | D9: ='附1-预算表'!H8 -> 0.050215916 | G9: 项目已发生成本（万元） | I9: 0
A10: 项目运维周期 | D10: / | G10: 是否存在转包限制（客户/客户上游禁止转包） | I10: 否
A11: 项目概述 | D11: 项目目的及建设目标： 立足原有数据建设基础，继续丰富时空数据资源。建设和更新一系列影像数据和矢量专题数据，确保数据的准确性和时效性。结合坪山区的实际需求，保障坪山区时空信息云平台正常运行，使之能够满足坪山区各局办日益增长的业务需求，更好支撑各单位业务应用。项目签一续三，今年是第三年。 采购范围及内容：本次采购服务项目范围包括对坪山区时空信息云平台相关数据更新服务，商业地图标注错误修复及时空信息云平台一年的保障服务。 一、数据服务： 1、分包原世界：①航空三维实景；③卫星影像；④底商纹理数据融合；⑤专题影像图制作；⑥地图打印及装裱。 2、丰图负责：⑦地名地址更新服务一次。 3、分包智信：⑧实体数据：不少于3类实体数据共2万个数据建设。 4、分包武测：⑨数据展示要求：对数据进行处理并导入平台进行展示。 二、保障服务（现场4人负责）：1.系统巡检；2.故障处理；3.特殊防护期保障；4.应急响应保障；5.提供数据备份服务；6.备品备件。
A12: 签约路径 | D12: 深圳市坪山区政务服务和数据管理局→丰图科技（深圳）有限公司
A13: 是否涉及测绘（涉及外业采集或地图） | D13: 是 | G13: 是否涉及甲导资质 | I13: 否
A14: 是否涉密项目（涉及保密资质） | D14: 否
A15: 分包总金额（万元） | D15: =1799036.92/10000 -> 179.90369 | G15: 指定类分包金额（万元） | I15: =1799036.92/10000 -> 179.90369
A16: 测绘类分包金额（万元） | D16: 0 | G16: 分包是否涉及公司核心能力 | I16: 否
A17: 项目推广激励面向对象 | D17: 无 | G17: 项目推广激励（万元） | I17: 0
A18: 结算方式 | D18: 银行转账 | G18: 预计回款时间 | I18: 预计26年Q3回款50%，27年Q2回款35%，27年Q3回款5%
A19: 付款条件 | D19: 第一次付款：服务方案通过甲方确认后，申请支付合同款 50%。 第二次付款：服务期满半年后，申请支付合同款 35%。 第三次付款：合同约定的服务期满后，经甲方确认乙方已全面履行了本合同义务并经甲方验收合格后申请支付合同剩余款项（剩余款项=合同价*15%-扣款金额-违约金）。
A20: 合同背靠背场景 | D20: 回款+验收=均非背靠背 | G20: 确收方式及预估确收时间 | I20: 2026.9-2027.8，按月分摊确收110.9万元，终验确收其他份额，预计27年Q3终验
A21: 合同是否存在提供担保或为他人提供担保 | D21: 否 | G21: 合同是否存在竞业条款 | I21: 否
A22: 合同是否有转包限制 | D22: 否 | G22: 项目是否涉及硬件所有权归属 | I22: 否
A23: 是否涉及SF小哥相关业务 | D23: 否 | G23: 是否涉及数据跨境传输或红线禁止数据 | I23: 否
A24: 项目所在地省份 | D24: 广东省 | G24: 产品售卖类型 | I24: 非标品
A25: B2业务类型 | D25: 请选择 | G25: 标品售价标准 | I25: 不涉及标品
A27: Part B：非量化类关键评审指标-前置评审
A28: 序号 | B28: 评审维度 （部门） | C28: 评判指标 | D28: 辅助指标/说明 | E28: 绿灯标准 （免上会） | F28: 黄灯标准 （上会决策） | H28: 红灯标准 （红线禁止） | I28: 风险等级 （红/黄/绿） | J28: 前置评审意见 | K28: 前置评审人 （签字）
I29: 部门评审↓ | J29: 部门评审↓ | K29: 部门评审↓
A30: 1 | B30: 业务/采购 | C30: 分包合理性 | D30: 分包能力是否核心能力、是否指定性、付款条款不合理、下游分包方资质 | E30: 非公司核心能力分包，且非指定性分包、测绘类项目下游分包方有测绘资质、付款条款为背靠背、供应商资质合格 | F30: 公司核心能力被分包（指定性分包需上XO级）、付款条款不为背靠背、测绘类项目下游供应商无测绘资质、供应商资质不合格等 | I30: 绿灯 | J30: 三个指定分包金额为客户指定价格，请业务部分确认。 1、三维数据更新：指定深圳原世界科技有限公司，48.7万。 ①资质：原世界为公司常合作供应商，有测绘相关资质，历史合作良好。 ②成本：经线下沟通本次采购价格为客户指定价格。 2、城市实体数据采集：指定北京智信遥感地理信息技术有限公司，16.6万。 ①资质：北京智信为2025年城市实体数据采集分包商，历史合作良好，资质满足要去。 ②成本：经线下沟通本次采购价格为客户指定价格。 3、系统运维：深圳市武测空间信息有限公司，分包内容平台运维服务，3.5万元。 ①资质：深圳武测为2025年系统运维分包商，历史合作良好，履约无问题。 ②成本：经线下沟通本次采购价格为客户指定价格。 4、人力外包（110.9万）：项目分包服务人员4名，历史采用岗位外包服务模式与库内供应商恒英合作，目前稳定服务中。 | K30: 采购BP/FDE
A31: 2 | B31: 业务 | C31: 技术可行性 | E31: 无技术风险 | F31: 存在交付侧技术风险，但在客户需求边界/预期交付边界控制情况下可完成交付 | H31: 技术侧无法交付，因成本/资质问题无法分包 | I31: 绿灯 | J31: 同意 | K31: FDE工程师
A32: 3 | B32: 财务 | C32: 客户历史欠款 | D32: 逾期天数/逾期金额 | E32: 无；或存在终验款和质保金逾期，销售愿意背书在90天内拿回终验款 | F32: 其他逾期款情况 | I32: 黄灯 | J32: 25年合同的半年款还未回完，13万逾期未回，仅同意逾期款回后签合同 | K32: 财务BP
A33: 4 | B33: 财务 | C33: 签约客户/最终客户信用评估 | D33: 客户评级制度、工商公开信息等 | E33: 政府/央企/国有企业等优质客户 非国有小微企业满足：成立≥5年、人员≥10、近三月有中标、法人无失信、无诉讼 | F33: "皮包公司"或财政和资金状况较差 | H33: 黑名单客户 | I33: 绿灯 | K33: 财务BP
A34: 5 | B34: 财务 | C34: 集团公司关联交易金额 | D34: 年度关联交易预算金额 | E34: 累计关联交易预算金额≤100w | F34: 累计关联交易预算金额＞100w | I34: 绿灯 | K34: 财务BP
A35: 6 | B35: 财务 | C35: 付款条件 | E35: 1、明确有预付款条款，且约定具体付款期间 2、硬件销售部分100%预付 3、软件销售部分100%预付或**%预付，验收后10日内支付剩余 | F35: 1、无预付条款，或无约定具体付款期间 2、硬件销售部分非100%预付，但无垫资（供应商承担） 3、软件销售部分不满足免上会条件，且非背靠背 | H35: 1、硬件销售部分非100%预付，存在垫资 2、软件销售部分为背靠背 | I35: 黄灯 | J35: 1、毛利风险较低：贡毛＞0%，高于基准线； 2、回款风险较低：政府直签项目，为续签项目，但25年合同的半年款还未回完，13万逾期未回，仅同意逾期款回后签合同，此客户其他款项回款情况良好； 3、售前投入：截止到2026年7月31日，无交付投入； 4、确收方式：分摊+终验确收； 5、回款条件：方案确认50%，满半年35%，服务期满15%（预计26年回款50%） | K35: 财务BP
A36: 7 | B36: 法务 | C36: 上游签约路径公司情况 | D36: 异常经营记录、营业执照、失信名单、与丰图之间是否存在诉讼、被执行记录、行政处罚记录 | E36: 1、无异常记录 2、与丰图无诉讼案件；或诉讼中丰图为第三人，不涉及义务承担 3、无被执行记录；或已执行完毕且与项目无关 4、无处罚记录；或非近三年已履行完毕且与项目无关 | F36: 1、与丰图有诉讼案件，但丰图为第三人涉及义务承担、已判决/和解但款项未完全支付、或已完结 2、有执行纪录，近三年已执行完毕，与项目相关或涉及金钱给付 3、有行政处罚纪录，但近三年已履行完毕且与项目无关或不涉及资质处罚 | H36: 1、存在异常经营记录；营业执照被吊销；列入失信名单；被提起破产清算等 2、与丰图有诉讼案件，且丰图作为原告/被告，未开庭/未和解 3、有执行纪录，且执行中状态；未履行义务；列入失信被执行人 4、有行政处罚纪录，且未履行完毕；涉及资质处罚 | I36: 绿灯 | J36: 1.截至20260811，坪山政数局与丰图之间不存在诉讼，无相关异常情形； 2.25年项目合同中有根据履约评价续签条款，约定：协议期内所有合同实质性条款不得改变。双方每签一年协议后需到坪山区财政局备案。请业务侧注意跟进。 | K36: 法务
A37: 8 | B37: 法务 | C37: 转包限制风险 | D37: 客户转包或丰图直签分包限制 | E37: 丰图内部关联交易无需二次评审 | F37: 有背靠背转移风险约定且可转移给供应商 | H37: 背靠背约定但丰图自行交付/供应商无法满足风险转移，违约责任超X万 | I37: 绿灯 | J37: 指定分包+延续上一年供应商 | K37: 法务
A38: 9 | B38: 合规 | C38: 合规风险 | D38: 甲测/甲导资质风险、审图风险 | E38: 1. 无风险； 2. 已有管控举措。风险可控，不影响丰图资质。 | F38: 1. 风险存在不确定性； 2. 对资质存在明确影响，但不严重，影响范围可接受。 | H38: 对资质存在明确影响，非常严重，影响范围不可接受。 | I38: 绿灯 | J38: 分包由甲方指定。 | K38: 合规

Sheet 附1-预算表
A1: 坪山区三维数据更新2026-预算表（项目经理提供数据； 单位：元）
A2: 所属部门 | B2: 泛政务一部 | C2: 项目名称（内部） | D2: 坪山区三维数据更新2026 | E2: 商务经理 | F2: 熊惠 | G2: 项目经理 | H2: 邓先明 | I2: 渠道调节系数 | J2: 1
A3: 所属营销大区 | B3: 华南营销处 | C3: 客户名称 | D3: 深圳市坪山区政务服务和数据管理局 | E3: 商机代码 | F3: PL00008111 | G3: 项目代码 | H3: / | I3: 预计签单时间 | J3: 46266
A4: 预计开始时间 | B4: 46266 | C4: 预计终验时间 | D4: 46631 | E4: 运维周期（质保期） | F4: / | G4: 项目阶段 | H4: 投标决策 | I4: 项目难度系数 | J4: 1
A5: 成本测算 | B5: 合同金额 | D5: 项目收入 | E5: 分包采购成本 | F5: 软件类生产外包 | G5: 项目净收入 | H5: 交付成本 （含数据类生产外包） | I5: 标品成本
B6: 2058520 | D6: =B6/(1+6%) -> 1942000 | E6: =G10 -> 1799036.9 | F6: =G11 -> 0 | G6: =D6-(E6+F6)/1.06-B8 -> 244795.36 | H6: =SUM(G19:G28) -> 51603 | I6: ='附3-交付成本评估'!CK2 -> 0
A7: 毛利/率测算 | B7: 项目推广激励（灵活用工） | D7: 销售成本 （含税金，不含激励） | E7: 销售考核利润 （含税金，不含激励） | F7: 销售考核毛利率 | G7: 贡献毛利 （已扣除激励） | H7: 贡献毛利率 | I7: 交付成本占净收入比 （与决算偏差±10%以内） | J7: 销售总成本占净收入比
B8: =G12 -> 0 | D8: =SUM(G13:G17) -> 83232.728 | E8: =G6-D8 -> 161562.63 | F8: =E8/D6 -> 0.08319394 | G8: =G6-D8-H6-G18 -> 97519.308 | H8: =G8/D6 -> 0.050215916 | I8: =H6/G6 -> 0.21080057 | J8: =SUM(G13:G18)/G6 -> 0.39082869
A9: 序号 | B9: 成本大类 | D9: 成本小类 | E9: 计算逻辑说明 | G9: 成本小计 | H9: 成本占项目收入比 | I9: 成本评估备注
A10: 1 | B10: 分成分包 | D10: / | E10: 1、项目集成分包、项目日常运维分包费用 2、定制化软件开发的分包费用 3、技术服务费 | G10: 1799036.9 | H10: =G10/1.06/$D$6 -> 0.87394678 | I10: 指定分包1：深圳原世界科技有限公司，分包金额48.7万。 分包内容： 1.采购坪山实景三维更新 ①更新区域不少于10平方公里，包括2cm地物分辨率不少于4平方公里，5cm地物分辨率不少于6平方公里。 ②全区168平方公里的二维正射影像采集。 ③对航空三维实景重点更新区域的模型底商纹理进行融合，保证实景三维模型数据底商纹理完整清晰。 ④专题影像图制作和打印，11幅。 2.采购全区卫星影像采集2幅，要求具备红外波段。 3.数据质检。 4.专家技术评审。 指定分包2：北京智信遥感地理信息技术有限公司，分包金额16.6万。 分包内容：采购完成工地实体、产业园区实体、摄像头实体数据接入处理。 指定分包3：深圳市武测空间信息有限公司，分包内容平台运维服务，3.5万元。 非指定分包4：备品备件（移动盘，用于存储数据），0.2万元。 非指定分包5：驻点人员费用包，110.903692万元。
B11: 软件类生产外包 | D11: / | E11: 软件类生产相关的内、外业人员的生产外包人力成本 | G11: ='附3-交付成本评估'!BF2+'附3-交付成本评估'!BL2+'附3-交付成本评估'!CB2+'附3-交付成本评估'!CH2 -> 0 | H11: =G11/$D$6 -> 0 | I11: 丰图产品不具备交付能力但是从项目层面需要进行包装整合。比如三维建模，BIM数据生产。
B12: 项目推广激励（灵活用工） | D12: / | E12: 小创云等灵活用工平台的费用预算 | G12: 0 | H12: =G12/$D$6 -> 0 | I12: 从净收入中剔除，即【净收入=收入-分包-软件类生产外包-灵活用工】
A13: 2 | B13: 销售成本 | C13: 人力成本 | D13: 自有人员 | E13: 自有市场营销部人员成本（含销售、解决方案、CMO办公室、招投标组人力成本） | G13: =(B6-E6)/10000*1727 -> 44812.728 | H13: =G13/$D$6 -> 0.023075555 | I13: 按财务最新发布，26年销售人力标准成本=净签单/万*1727元。 示例：某项目合同总额500万，分包300万，26年销售人力标准成本=（500-300）*1727=345400元。
C14: 销售费用包 | D14: 差旅费 | E14: 项目客户拜访等发生的差旅（需包含解决方案成本） | G14: 12000 | H14: =G14/$D$6 -> 0.0061791967
D15: 招待费 | E15: 项目客户拜访等发生的招待费用（需包含解决方案成本） | G15: 7000 | H15: =G15/$D$6 -> 0.0036045314
D16: 市场营销 | E16: 市场营销费用、投标阶段的专家费等 | H16: =G16/$D$6 -> 0
D17: 税金 | E17: 税后收入*1％（已设置公式，自动计算） | G17: =D6*1% -> 19420 | H17: =G17/$D$6 -> 0.01
D18: 销售及售前激励 | E18: 销售考核利润（不含激励）*7.7%（包含销售与售前的激励） （已设置公式，自动计算） | G18: =E8*7.7% -> 12440.323 | H18: =G18/$D$6 -> 0.0064059333 | I18: *部分银行项目销售及售前激励=销售考核利润（不含激励）*5.7%*0.4
A19: 3 | B19: 交付成本 | C19: 人力成本 | D19: 自有人员 | E19: 1、用于本项目交付实施的技术架构、研发、产品经理、交付运营、测试、运维等自有员工成本（需包含项目运维成本） | G19: ='附3-交付成本评估'!P2+'附3-交付成本评估'!BW2 -> 23744 | H19: =G19/$D$6 -> 0.012226571 | I19: 1）泛政业务一部26年标准成本： ①自有人天-交付处：1,696元/天 ②自有人天-行业拓展处：2303元/天 2）企业服务发展部26年标准成本： ①自有人天-公共服务业务处：2204元/天 ②自有人天-行业售前方案处：2350元/天 ③自有人天-企业产品研发处：3001元/天 3）基础平台产品部26年标准成本： ①自有人天-数据产品处：1720元/天 ②自有人天-智能地图处：1752元/天 ③自有人天-公共组件处：1374元/天
D20: 研发外包 | E20: 1、用于本项目交付实施的项目助理、研发、产品经理、交付运营、测试、运维等外包员工成本 | G20: ='附3-交付成本评估'!Q2+'附3-交付成本评估'!BX2 -> 4975 | H20: =G20/$D$6 -> 0.002561792 | I20: 1）泛政业务一部26年标准成本： ①研发外包：995元/天； 2）企业服务发展部26年标准成本： ①研发外包：1,022元/人天；
C21: 生产人员成本 | D21: 数据类生产外包 | E21: 数据类生产相关的内、外业人员的生产外包人力成本 | G21: ='附3-交付成本评估'!BD2+'附3-交付成本评估'!BK2+'附3-交付成本评估'!BZ2+'附3-交付成本评估'!CG2 -> 9600 | H21: =G21/$D$6 -> 0.0049433574 | I21: 丰图产品具备交付能力只是用了生产资源来执行交付。比如地址治理，地图生产，数据服务交付运营等
C22: 差旅招待 | D22: 差旅费 | E22: 项目实施人员出差的长途交通费+补助+住宿费（酒店、租房、物业水电费） | G22: ='附3-交付成本评估'!BJ2+'附3-交付成本评估'!CF2 -> 0 | H22: =G22/$D$6 -> 0
C23: 项目管理费 | D23: 自有人员 | E23: 项目经理自有人员人力成本 | G23: ='附3-交付成本评估'!X2+'附3-交付成本评估'!BT2 -> 6784 | H23: =G23/$D$6 -> 0.0034933059
D24: 差旅、市内交通 | E24: 差旅、市内交通 | G24: ='附3-交付成本评估'!BH2+'附3-交付成本评估'!CD2 -> 2000 | H24: =G24/$D$6 -> 0.0010298661
D25: 招待费 | E25: 关键里程碑、验收推动招待费用 | G25: ='附3-交付成本评估'!BI2+'附3-交付成本评估'!CE2 -> 0 | H25: =G25/$D$6 -> 0
D26: 项目验收 | E26: 项目技术评审专家费等 | H26: =G26/$D$6 -> 0
D27: 综合办公 | E27: 项目资料打印、资料邮寄、设备邮寄相关的快递费；项目实施需要采购的办公耗材，如插线板、路由器等；办公资产采购等 | G27: 4500 | H27: =G27/$D$6 -> 0.0023171988 | I27: 1.快递费500元 2.打印费3000元 3.办公耗材1000元
D28: 专业服务 | E28: 审计律师费用、顾问费用、其它咨询费用 | H28: =G28/$D$6 -> 0
A29: 制表人： | B29: 邓先明 | E29: 复核人： | G29: 沈路
A30: 填写说明：标黄的部分为需人工填写，白色区域有公式带出对应数值。

Sheet 附3-交付成本评估
A1: 项目名称：2026年时空信息云平台数据更新服务项目
A2: 合计值 | J2: =SUM(J5:J14) -> 0 | K2: =SUM(K5:K14) -> 0 | L2: =SUM(L5:L14) -> 0 | M2: =SUM(M5:M14) -> 0 | N2: =SUM(N5:N14) -> 45103 | O2: =SUM(O5:O14) -> 6784 | P2: =SUM(P5:P14) -> 23744 | Q2: =SUM(Q5:Q14) -> 4975 | ... BL2: =SUM(BL5:BL14) -> 0 | BN2: =SUM(BN5:BN14) -> 0 | BO2: =SUM(BO5:BO14) -> 0 | BP2: =SUM(BP5:BP14) -> 0 | BQ2: =SUM(BQ5:BQ14) -> 0 | BR2: =SUM(BR5:BR14) -> 0 | BS2: =SUM(BS5:BS14) -> 0 | BT2: =SUM(BT5:BT14) -> 0 | BU2: =SUM(BU5:BU14) -> 0 | ... CH2: =SUM(CH5:CH14) -> 0 | CJ2: =SUM(CJ5:CJ14) -> 0 | CK2: =SUM(CK5:CK14) -> 0
A3: 序号 | B3: 解决方案评估 | I3: 标品研发负责人评估 | J3: 1.0 实施阶段- 销售成本 | N3: 1.1 实施阶段- 交付人力成本 | W3: ① 项目经理： | Y3: ② 产品售前岗： | AC3: ③ 产 品 岗： | AG3: ④ 前 端 岗： | AK3: ⑤ 后 端 岗： | AO3: ⑥ 大数据开发岗： | AS3: ⑦ 交 付 岗： | AW3: ⑧ 架 构： | AY3: ⑨ 其他：测试、UI、实施中运维投入 | BC3: ⑩ 生产外包-数据类： | BE3: ⑪ 生产外包-软件类： | BG3: 1.2 实施阶段- 交付差旅招待 | BM3: ★工作量评估负责人 （可补充说明成本评估备注） | BN3: 2.0 运维阶段- 销售成本 | BR3: 2.1 运维阶段-人力成本： | BS3: ① 项 目 经 理： | BU3: ② 产 研 投 入： | BY3: ③ 生产外包-数据类： | CA3: ④ 生产外包-软件类： | CC3: 2.2 运维阶段-差旅成本 | CI3: 按岗位人员投入人数说明 | CJ3: 标品
B4: 建设内容 | C4: 对应标准产品名称 （下拉选择） | D4: 建设内容-细分模块 | E4: 具体功能项 | F4: 功能描述 | G4: 最终交付物 | H4: 交付方式 | I4: 是否标品交付 | J4: 销售-人力成本 | K4: 销售-差旅 | L4: 销售-招待费 | M4: 销售-市场营销 | N4: 实施阶段- 人力成本总额 | O4: ① 实施阶段- 人力成本总额 （项目经理） | P4: ② 实施阶段- 人力成本总额 （产研正编） | Q4: ③ 实施阶段- 人力成本总额 （产研外包） | R4: ④ 实施阶段- 人力成本总额 （生产外包） | S4: 实施阶段- 人天汇总 （项目经理） | T4: 实施阶段- 人天汇总 （产研正编） | U4: 实施阶段- 人天汇总 （产研外包） | V4: 实施阶段- 人天汇总 （生产外包） | W4: 项目经理 正编人天 | X4: 项目经理 正编金额 | Y4: 产品售前 正编人天 | Z4: 产品售前 外包人天 | AA4: 产品售前 正编金额 | AB4: 产品售前 外包金额 | AC4: 产品 正编人天 | AD4: 产品 外包人天 | AE4: 产品 正编金额 | AF4: 产品 外包金额 | AG4: 前端 正编人天 | AH4: 前端 外包人天 | AI4: 前端 正编金额 | AJ4: 前端 外包金额 | AK4: 后端 正编人天 | AL4: 后端 外包人天 | AM4: 后端 正编金额 | AN4: 后端 外包金额 | AO4: 大数据开发 正编人天 | AP4: 大数据开发 外包人天 | AQ4: 大数据开发 正编金额 | AR4: 大数据开发 外包金额 | AS4: 交付 正编人天 | AT4: 交付 外包人天 | AU4: 交付 正编金额 | AV4: 交付 外包金额 | AW4: 架构 正编人天 | AX4: 架构 正编金额 | AY4: 其他 正编人天 | AZ4: 其他 外包人天 | BA4: 其他 正编金额 | BB4: 其他 外包金额 | BC4: 生产外包 人天 | BD4: 生产外包 金额 | BE4: 生产外包 人天 | BF4: 生产外包 金额 | BG4: 实施阶段- 差旅成本总额 | BH4: 实施阶段-差旅成本 项目经理-差旅、市内交通 | BI4: 实施阶段-差旅成本 项目经理-招待费 | BJ4: 实施阶段-差旅成本 产研（正编+外包） | BK4: 实施阶段-差旅成本 生产外包（数据类） | BL4: 实施阶段-差旅成本 生产外包（软件类） | BN4: 销售-人力成本 | BO4: 销售-差旅 | BP4: 销售-招待费 | BQ4: 销售-市场营销 | BR4: 运维阶段- 人力成本总额 | BS4: 项目经理 正编人天 | BT4: 项目经理 正编金额 | BU4: 产研 正编人天 | BV4: 产研 外包人天 | BW4: 产研 正编金额 | BX4: 产研 外包金额 | BY4: 生产外包 人天 | BZ4: 生产外包 金额 | CA4: 生产外包 人天 | CB4: 生产外包 金额 | CC4: 运维阶段- 差旅成本总额 | CD4: 运维阶段-差旅成本 项目经理-差旅、市内交通 | CE4: 运维阶段-差旅成本 项目经理-招待费 | CF4: 运维阶段-差旅成本 产研（正编+外包） | CG4: 运维阶段-差旅成本 生产外包（数据类） | CH4: 运维阶段-差旅成本 生产外包（软件类） | CJ4: 人天 | CK4: 金额 | CL4: 标品成本评估-说明
A5: 1 | B5: 运维服务 | I5: 否 | N5: =O5+P5+Q5+R5 -> 6784 | O5: =X5 -> 6784 | P5: =AA5+AE5+AI5+AM5+AQ5+AU5+AX5+BA5 -> 0 | Q5: =AB5+AF5+AJ5+AN5+AR5+AV5+BB5 -> 0 | R5: =BD5+BF5 -> 0 | S5: =W5 -> 4 | T5: =Y5+AC5+AG5+AK5+AO5+AS5+AW5+AY5 -> 0 | U5: =Z5+AD5+AH5+AL5+AP5+AT5+AZ5 -> 0 | V5: =BC5+BE5 -> 0 | W5: 4 | X5: =W5*1696 -> 6784 | AB5: =Z5*995 -> 0 | AF5: =AD5*995 -> 0 | AJ5: =AH5*995 -> 0 | AN5: =AL5*995 -> 0 | AR5: =AP5*995 -> 0 | AV5: =AT5*995 -> 0 | BB5: =AZ5*995 -> 0 | BD5: =BC5*320 -> 0 | BF5: =BE5*320 -> 0 | BG5: =SUM(BH5:BL5) -> 2000 | BH5: 2000 | BR5: =SUM(BT5,BW5,BX5,BZ5,CB5) -> 0 | BX5: =BV5*995 -> 0 | BZ5: =BY5*320 -> 0 | CB5: =CA5*320 -> 0 | CC5: =SUM(CD5:CH5) -> 0 | CI5: 岗位（正编/外包）：人数+对应投入人天 ①产品岗：正编投入_人；外包投入_人 ②前端岗：正编投入_人；外包投入_人 ③后端岗：正编投入_人；外包投入_人 ④大数据开发：正编投入_人；外包投入_人 ⑤交付岗：正编投入_人 ⑥架构岗：正编投入_人；外包投入_人 ⑦其他：正编投入_人；外包投入_人 ...... | CL5: 产品、研发：
A6: 2 | B6: 地名地址更新服务 | D6: 根据坪山区地名地址数据建设情况进行数据更新，服务期内更新1次 | G6: 1.融合治理后的标准地址数据（csv） 2.更新后的地址服务索引（geo、rgeo、大搜索引） | I6: 否 | N6: =O6+P6+Q6+R6 -> 38319 | O6: =X6 -> 0 | P6: =AA6+AE6+AI6+AM6+AQ6+AU6+AX6+BA6 -> 23744 | Q6: =AB6+AF6+AJ6+AN6+AR6+AV6+BB6 -> 4975 | R6: =BD6+BF6 -> 9600 | S6: =W6 -> 0 | T6: =Y6+AC6+AG6+AK6+AO6+AS6+AW6+AY6 -> 14 | U6: =Z6+AD6+AH6+AL6+AP6+AT6+AZ6 -> 5 | V6: =BC6+BE6 -> 30 | AB6: =Z6*995 -> 0 | AF6: =AD6*995 -> 0 | AJ6: =AH6*995 -> 0 | AN6: =AL6*995 -> 0 | AR6: =AP6*995 -> 0 | AS6: 12 | AT6: 5 | AU6: =AS6*1696 -> 20352 | AV6: =AT6*995 -> 4975 | AY6: 2 | BA6: =AY6*1696 -> 3392 | BB6: =AZ6*995 -> 0 | BC6: 30 | BD6: =BC6*320 -> 9600 | BF6: =BE6*320 -> 0 | BG6: =SUM(BH6:BL6) -> 0 | BR6: =SUM(BT6,BW6,BX6,BZ6,CB6) -> 0 | BX6: =BV6*995 -> 0 | BZ6: =BY6*320 -> 0 | CB6: =CA6*320 -> 0 | CC6: =SUM(CD6:CH6) -> 0
A7: 3 | B7: 地图错误修复 | D7: 追踪时空云平台和主流商业地图在坪山区内错误、过时的地图数据。 | G7: 主流地图问题纠错报告 | I7: 否 | N7: =O7+P7+Q7+R7 -> 0 | O7: =X7 -> 0 | P7: =AA7+AE7+AI7+AM7+AQ7+AU7+AX7+BA7 -> 0 | Q7: =AB7+AF7+AJ7+AN7+AR7+AV7+BB7 -> 0 | R7: =BD7+BF7 -> 0 | S7: =W7 -> 0 | T7: =Y7+AC7+AG7+AK7+AO7+AS7+AW7+AY7 -> 0 | U7: =Z7+AD7+AH7+AL7+AP7+AT7+AZ7 -> 0 | V7: =BC7+BE7 -> 0 | AB7: =Z7*995 -> 0 | AF7: =AD7*995 -> 0 | AJ7: =AH7*995 -> 0 | AN7: =AL7*995 -> 0 | AR7: =AP7*995 -> 0 | AV7: =AT7*995 -> 0 | BB7: =AZ7*995 -> 0 | BD7: =BC7*320 -> 0 | BF7: =BE7*320 -> 0 | BG7: =SUM(BH7:BL7) -> 0 | BR7: =SUM(BT7,BW7,BX7,BZ7,CB7) -> 0 | BX7: =BV7*995 -> 0 | BZ7: =BY7*320 -> 0 | CB7: =CA7*320 -> 0 | CC7: =SUM(CD7:CH7) -> 0
A8: 4 | N8: =O8+P8+Q8+R8 -> 0 | O8: =X8 -> 0 | P8: =AA8+AE8+AI8+AM8+AQ8+AU8+AX8+BA8 -> 0 | Q8: =AB8+AF8+AJ8+AN8+AR8+AV8+BB8 -> 0 | R8: =BD8+BF8 -> 0 | S8: =W8 -> 0 | T8: =Y8+AC8+AG8+AK8+AO8+AS8+AW8+AY8 -> 0 | U8: =Z8+AD8+AH8+AL8+AP8+AT8+AZ8 -> 0 | V8: =BC8+BE8 -> 0 | AB8: =Z8*995 -> 0 | AF8: =AD8*995 -> 0 | AJ8: =AH8*995 -> 0 | AN8: =AL8*995 -> 0 | AR8: =AP8*995 -> 0 | AV8: =AT8*995 -> 0 | BB8: =AZ8*995 -> 0 | BD8: =BC8*320 -> 0 | BF8: =BE8*320 -> 0 | BG8: =SUM(BH8:BL8) -> 0 | BR8: =SUM(BT8,BW8,BX8,BZ8,CB8) -> 0 | BX8: =BV8*995 -> 0 | BZ8: =BY8*320 -> 0 | CB8: =CA8*320 -> 0 | CC8: =SUM(CD8:CH8) -> 0
A9: 5 | N9: =O9+P9+Q9+R9 -> 0 | O9: =X9 -> 0 | P9: =AA9+AE9+AI9+AM9+AQ9+AU9+AX9+BA9 -> 0 | Q9: =AB9+AF9+AJ9+AN9+AR9+AV9+BB9 -> 0 | R9: =BD9+BF9 -> 0 | S9: =W9 -> 0 | T9: =Y9+AC9+AG9+AK9+AO9+AS9+AW9+AY9 -> 0 | U9: =Z9+AD9+AH9+AL9+AP9+AT9+AZ9 -> 0 | V9: =BC9+BE9 -> 0 | AB9: =Z9*995 -> 0 | AF9: =AD9*995 -> 0 | AJ9: =AH9*995 -> 0 | AN9: =AL9*995 -> 0 | AR9: =AP9*995 -> 0 | AV9: =AT9*995 -> 0 | BB9: =AZ9*995 -> 0 | BD9: =BC9*320 -> 0 | BF9: =BE9*320 -> 0 | BG9: =SUM(BH9:BL9) -> 0 | BR9: =SUM(BT9,BW9,BX9,BZ9,CB9) -> 0 | BX9: =BV9*995 -> 0 | BZ9: =BY9*320 -> 0 | CB9: =CA9*320 -> 0 | CC9: =SUM(CD9:CH9) -> 0
A10: 6 | N10: =O10+P10+Q10+R10 -> 0 | O10: =X10 -> 0 | P10: =AA10+AE10+AI10+AM10+AQ10+AU10+AX10+BA10 -> 0 | Q10: =AB10+AF10+AJ10+AN10+AR10+AV10+BB10 -> 0 | R10: =BD10+BF10 -> 0 | S10: =W10 -> 0 | T10: =Y10+AC10+AG10+AK10+AO10+AS10+AW10+AY10 -> 0 | U10: =Z10+AD10+AH10+AL10+AP10+AT10+AZ10 -> 0 | V10: =BC10+BE10 -> 0 | AB10: =Z10*995 -> 0 | AF10: =AD10*995 -> 0 | AJ10: =AH10*995 -> 0 | AN10: =AL10*995 -> 0 | AR10: =AP10*995 -> 0 | AV10: =AT10*995 -> 0 | BB10: =AZ10*995 -> 0 | BD10: =BC10*320 -> 0 | BF10: =BE10*320 -> 0 | BG10: =SUM(BH10:BL10) -> 0 | BR10: =SUM(BT10,BW10,BX10,BZ10,CB10) -> 0 | BX10: =BV10*995 -> 0 | BZ10: =BY10*320 -> 0 | CB10: =CA10*320 -> 0 | CC10: =SUM(CD10:CH10) -> 0
A11: 7 | N11: =O11+P11+Q11+R11 -> 0 | O11: =X11 -> 0 | P11: =AA11+AE11+AI11+AM11+AQ11+AU11+AX11+BA11 -> 0 | Q11: =AB11+AF11+AJ11+AN11+AR11+AV11+BB11 -> 0 | R11: =BD11+BF11 -> 0 | S11: =W11 -> 0 | T11: =Y11+AC11+AG11+AK11+AO11+AS11+AW11+AY11 -> 0 | U11: =Z11+AD11+AH11+AL11+AP11+AT11+AZ11 -> 0 | V11: =BC11+BE11 -> 0 | AB11: =Z11*995 -> 0 | AF11: =AD11*995 -> 0 | AJ11: =AH11*995 -> 0 | AN11: =AL11*995 -> 0 | AR11: =AP11*995 -> 0 | AV11: =AT11*995 -> 0 | BB11: =AZ11*995 -> 0 | BD11: =BC11*320 -> 0 | BF11: =BE11*320 -> 0 | BG11: =SUM(BH11:BL11) -> 0 | BR11: =SUM(BT11,BW11,BX11,BZ11,CB11) -> 0 | BX11: =BV11*995 -> 0 | BZ11: =BY11*320 -> 0 | CB11: =CA11*320 -> 0 | CC11: =SUM(CD11:CH11) -> 0
A12: 8 | N12: =O12+P12+Q12+R12 -> 0 | O12: =X12 -> 0 | P12: =AA12+AE12+AI12+AM12+AQ12+AU12+AX12+BA12 -> 0 | Q12: =AB12+AF12+AJ12+AN12+AR12+AV12+BB12 -> 0 | R12: =BD12+BF12 -> 0 | S12: =W12 -> 0 | T12: =Y12+AC12+AG12+AK12+AO12+AS12+AW12+AY12 -> 0 | U12: =Z12+AD12+AH12+AL12+AP12+AT12+AZ12 -> 0 | V12: =BC12+BE12 -> 0 | AB12: =Z12*995 -> 0 | AF12: =AD12*995 -> 0 | AJ12: =AH12*995 -> 0 | AN12: =AL12*995 -> 0 | AR12: =AP12*995 -> 0 | AV12: =AT12*995 -> 0 | BB12: =AZ12*995 -> 0 | BD12: =BC12*320 -> 0 | BF12: =BE12*320 -> 0 | BG12: =SUM(BH12:BL12) -> 0 | BR12: =SUM(BT12,BW12,BX12,BZ12,CB12) -> 0 | BX12: =BV12*995 -> 0 | BZ12: =BY12*320 -> 0 | CB12: =CA12*320 -> 0 | CC12: =SUM(CD12:CH12) -> 0
A13: 9 | N13: =O13+P13+Q13+R13 -> 0 | O13: =X13 -> 0 | P13: =AA13+AE13+AI13+AM13+AQ13+AU13+AX13+BA13 -> 0 | Q13: =AB13+AF13+AJ13+AN13+AR13+AV13+BB13 -> 0 | R13: =BD13+BF13 -> 0 | S13: =W13 -> 0 | T13: =Y13+AC13+AG13+AK13+AO13+AS13+AW13+AY13 -> 0 | U13: =Z13+AD13+AH13+AL13+AP13+AT13+AZ13 -> 0 | V13: =BC13+BE13 -> 0 | AB13: =Z13*995 -> 0 | AF13: =AD13*995 -> 0 | AJ13: =AH13*995 -> 0 | AN13: =AL13*995 -> 0 | AR13: =AP13*995 -> 0 | AV13: =AT13*995 -> 0 | BB13: =AZ13*995 -> 0 | BD13: =BC13*320 -> 0 | BF13: =BE13*320 -> 0 | BG13: =SUM(BH13:BL13) -> 0 | BR13: =SUM(BT13,BW13,BX13,BZ13,CB13) -> 0 | BX13: =BV13*995 -> 0 | BZ13: =BY13*320 -> 0 | CB13: =CA13*320 -> 0 | CC13: =SUM(CD13:CH13) -> 0
A14: 10 | N14: =O14+P14+Q14+R14 -> 0 | O14: =X14 -> 0 | P14: =AA14+AE14+AI14+AM14+AQ14+AU14+AX14+BA14 -> 0 | Q14: =AB14+AF14+AJ14+AN14+AR14+AV14+BB14 -> 0 | R14: =BD14+BF14 -> 0 | S14: =W14 -> 0 | T14: =Y14+AC14+AG14+AK14+AO14+AS14+AW14+AY14 -> 0 | U14: =Z14+AD14+AH14+AL14+AP14+AT14+AZ14 -> 0 | V14: =BC14+BE14 -> 0 | AB14: =Z14*995 -> 0 | AF14: =AD14*995 -> 0 | AJ14: =AH14*995 -> 0 | AN14: =AL14*995 -> 0 | AR14: =AP14*995 -> 0 | AV14: =AT14*995 -> 0 | BB14: =AZ14*995 -> 0 | BD14: =BC14*320 -> 0 | BF14: =BE14*320 -> 0 | BG14: =SUM(BH14:BL14) -> 0 | BR14: =SUM(BT14,BW14,BX14,BZ14,CB14) -> 0 | BX14: =BV14*995 -> 0 | BZ14: =BY14*320 -> 0 | CB14: =CA14*320 -> 0 | CC14: =SUM(CD14:CH14) -> 0
A16: 填写说明： 1、红色部分由解决方案填写，蓝色部分由项目经理填写，橙色部分由交付运营填写，绿色部分由产研侧填写 2、总成本=项目经理成本（含差旅）+交付实施成本（含差旅）+标品成本 3、人天单价参考（执行时间：2026年1月1日起）（以下均不区分级别）： ① 自有人天-交付处：1696元/天 自有人天-数据产品处：1720元/天 自有人天-智能地图处：1752元/天 自有人天-公共组件处：1374元/天 自有人天-公共服务业务处：2204元/天 自有人天-行业售前方案处：2350元/天 自有人天-企业产品研发处：3001元/天 ②研发外包人员-除企服以外：995元/天 研发外包人员-企服：1022元/天 ③生产外包人员（不区分级别）：320元/天
